odoo10_addon_base_cron_exclusion-10.0.1.0.0-py2.7-nspkg.pth
odoo/addons/base_cron_exclusion/README.rst
odoo/addons/base_cron_exclusion/__init__.py
odoo/addons/base_cron_exclusion/__manifest__.py
odoo/addons/base_cron_exclusion/models/__init__.py
odoo/addons/base_cron_exclusion/models/ir_cron.py
odoo/addons/base_cron_exclusion/views/ir_cron_view.xml
odoo10_addon_base_cron_exclusion-10.0.1.0.0.dist-info/DESCRIPTION.rst
odoo10_addon_base_cron_exclusion-10.0.1.0.0.dist-info/METADATA
odoo10_addon_base_cron_exclusion-10.0.1.0.0.dist-info/RECORD
odoo10_addon_base_cron_exclusion-10.0.1.0.0.dist-info/WHEEL
odoo10_addon_base_cron_exclusion-10.0.1.0.0.dist-info/metadata.json
odoo10_addon_base_cron_exclusion-10.0.1.0.0.dist-info/namespace_packages.txt
odoo10_addon_base_cron_exclusion-10.0.1.0.0.dist-info/top_level.txt
